rtctools_standard_library/__init__.py
rtc_tools_standard_library-0.1.1.dist-info/LICENSE
rtc_tools_standard_library-0.1.1.dist-info/METADATA
rtc_tools_standard_library-0.1.1.dist-info/WHEEL
rtc_tools_standard_library-0.1.1.dist-info/entry_points.txt
rtc_tools_standard_library-0.1.1.dist-info/top_level.txt
rtc_tools_standard_library-0.1.1.dist-info/RECORD
