Metadata-Version: 2.2
Name: rtc-tools-standard-library
Version: 0.1.1
Summary: Standard Modelica library for RTC-Tools ecosystem
Author-email: Joris Gillis <joris@yacoda.com>
License: BSD 3-Clause License
Project-URL: Repository, https://github.com/jgillis/rtc-tools-standard-library
License-File: LICENSE
